logic/__init__.py
logic/cli.py
logic/script.py
logic/states.py
logic/utilities.py
pyneweb-0.5.4.dist-info/LICENSE
pyneweb-0.5.4.dist-info/METADATA
pyneweb-0.5.4.dist-info/WHEEL
pyneweb-0.5.4.dist-info/entry_points.txt
pyneweb-0.5.4.dist-info/top_level.txt
pyneweb-0.5.4.dist-info/RECORD
