Metadata-Version: 2.1
Name: pyneweb
Version: 0.5.4
Summary: Web Boilerplate for Pynecone
Home-page: https://github.com/LineIndent/pyneweb
Author: S. Ahmad P. Hakimi
Author-email: pourhakimi@pm.me
Keywords: python web template,web application,development
Classifier: Programming Language :: Python :: 3
Classifier: License :: OSI Approved :: MIT License
Classifier: Operating System :: OS Independent
License-File: LICENSE
Requires-Dist: click (==8.1.3)
Requires-Dist: pynecone (==0.1.28)
Requires-Dist: PyYAML (==6.0)
